deeptracepy/DeepTrace.py
deeptracepy/DeepTraceClient.py
deeptracepy/Trace.py
deeptracepy/__init__.py
deeptracepy-0.1.0.dist-info/LICENSE
deeptracepy-0.1.0.dist-info/METADATA
deeptracepy-0.1.0.dist-info/WHEEL
deeptracepy-0.1.0.dist-info/top_level.txt
deeptracepy-0.1.0.dist-info/RECORD
