Metadata-Version: 2.1
Name: deeptracepy
Version: 0.1.0
Summary: DeepTrace client for python
Home-page: UNKNOWN
Author: Italo José G. de Oliveira
Author-email: italo.i@live.com
License: MIT license
Keywords: deetptrace
Platform: UNKNOWN
Classifier: Intended Audience :: Developers
Classifier: License :: OSI Approved :: MIT License
Classifier: Natural Language :: English
Classifier: Programming Language :: Python :: 3.4
Classifier: Programming Language :: Python :: 3.5
Classifier: Programming Language :: Python :: 3.6
Classifier: Programming Language :: Python :: 3.7
Requires-Dist: requests (==2.21.0)
